{
  "main": {
    "id": "a95bba9e53a6974b",
    "type": "split",
    "children": [
      {
        "id": "79c4ac7ddd2e020a",
        "type": "tabs",
        "children": [
          {
            "id": "eda72d3af3bbc704",
            "type": "leaf",
            "state": {
              "type": "graph",
              "state": {},
              "icon": "lucide-git-fork",
              "title": "Graph view"
            }
          }
        ]
      }
    ],
    "direction": "vertical"
  },
  "left": {
    "id": "65ec19afcf08ecf2",
    "type": "split",
    "children": [
      {
        "id": "756f41b05c4ca648",
        "type": "tabs",
        "children": [
          {
            "id": "7fe8b734cb23e048",
            "type": "leaf",
            "state": {
              "type": "file-explorer",
              "state": {
                "sortOrder": "alphabetical"
              },
              "icon": "lucide-folder-closed",
              "title": "Files"
            }
          },
          {
            "id": "3a9e27df04e8e264",
            "type": "leaf",
            "state": {
              "type": "search",
              "state": {
                "query": "",
                "matchingCase": false,
                "explainSearch": false,
                "collapseAll": false,
                "extraContext": false,
                "sortOrder": "alphabetical"
              },
              "icon": "lucide-search",
              "title": "Search"
            }
          },
          {
            "id": "1959826d592d7c7d",
            "type": "leaf",
            "state": {
              "type": "bookmarks",
              "state": {},
              "icon": "lucide-bookmark",
              "title": "Bookmarks"
            }
          }
        ]
      }
    ],
    "direction": "horizontal",
    "width": 300,
    "collapsed": true
  },
  "right": {
    "id": "bde9922bcc048060",
    "type": "split",
    "children": [
      {
        "id": "c613bd058c890df7",
        "type": "tabs",
        "children": [
          {
            "id": "ea04c65d63fdc390",
            "type": "leaf",
            "state": {
              "type": "backlink",
              "state": {
                "file": "C formatted output.md",
                "collapseAll": false,
                "extraContext": false,
                "sortOrder": "alphabetical",
                "showSearch": false,
                "searchQuery": "",
                "backlinkCollapsed": false,
                "unlinkedCollapsed": true
              },
              "icon": "links-coming-in",
              "title": "Backlinks for C formatted output"
            }
          },
          {
            "id": "2c383ea1e10f4481",
            "type": "leaf",
            "state": {
              "type": "outgoing-link",
              "state": {
                "file": "C formatted output.md",
                "linksCollapsed": false,
                "unlinkedCollapsed": true
              },
              "icon": "links-going-out",
              "title": "Outgoing links from C formatted output"
            }
          },
          {
            "id": "4b949134a61e066f",
            "type": "leaf",
            "state": {
              "type": "tag",
              "state": {
                "sortOrder": "frequency",
                "useHierarchy": true
              },
              "icon": "lucide-tags",
              "title": "Tags"
            }
          },
          {
            "id": "e53127f0f51158b2",
            "type": "leaf",
            "state": {
              "type": "outline",
              "state": {
                "file": "C formatted output.md"
              },
              "icon": "lucide-list",
              "title": "Outline of C formatted output"
            }
          },
          {
            "id": "479fbc168e8a2e88",
            "type": "leaf",
            "state": {
              "type": "git-view",
              "state": {},
              "icon": "git-pull-request",
              "title": "Source Control"
            }
          },
          {
            "id": "6ccd0e13241b3e24",
            "type": "leaf",
            "state": {
              "type": "advanced-tables-toolbar",
              "state": {},
              "icon": "spreadsheet",
              "title": "Advanced Tables"
            }
          }
        ],
        "currentTab": 4
      }
    ],
    "direction": "horizontal",
    "width": 246.5
  },
  "left-ribbon": {
    "hiddenItems": {
      "switcher:Open quick switcher": false,
      "graph:Open graph view": false,
      "canvas:Create new canvas": false,
      "daily-notes:Open today's daily note": false,
      "templates:Insert template": false,
      "command-palette:Open command palette": false,
      "obsidian-git:Open Git source control": false,
      "table-editor-obsidian:Advanced Tables Toolbar": false,
      "obsidian-file-cleaner:Clean files": false
    }
  },
  "active": "eda72d3af3bbc704",
  "lastOpenFiles": [
    "Code/C,C++/Arrow operator.md",
    "Code/C,C++/Typedef.md",
    "Index.md",
    "To-do.md",
    "Code/C,C++/Command line arguments.md",
    "To-do notes/USB PD.md",
    "MCUs/Arduino/Embeded/Low level blink sketch.md",
    "MCUs/Arduino/Embeded/Arduino register manipulation.md",
    "MCUs/Arduino/Arduino code execution timer.md",
    "Gay porn/Pulse width modulation.md",
    "Gay porn/Sine approximation/Taylor's series & sine approximation.md",
    "Code/C,C++/CMD code execution.md",
    "attachments/Screenshot 2024-10-15 001038.png",
    "Code/C,C++/Union.md",
    "Code/C,C++/Pointers/8) Pointers & dynamic memory.md",
    "Code/C,C++/Function-like macros.md",
    "Gay porn/Sine approximation/Sine LUT analysis.md",
    "Inline functions.md",
    "C formatted output.md",
    "Gay porn/Sine approximation/Optimizing sine LUT.md",
    "Gay porn/Sine approximation/Sine lookup table (LUT).md",
    "Gay porn/Binary & Hex/3) Signed bits.md",
    "Gay porn/Binary & Hex/2) Bitwise operations.md",
    "Gay porn/Binary & Hex/Hexadecimals.md",
    "Gay porn/Binary & Hex/1) The binary system.md",
    "attachments/Z-SCORE DISTRIBUTION.svg",
    "attachments/Error against Angle (1).svg",
    "attachments/Error against Angle.svg",
    "attachments/NORMAL DISTRIBUTION.svg",
    "attachments/Absolute Error against Angle.svg",
    "attachments/chart (1).svg",
    "To-do notes/Shift registers.md",
    "MCUs/STM32/STM32 PWM.md",
    "attachments/chart.svg",
    "attachments/low-res2.png",
    "attachments/Screenshot 2024-10-15 115246 1.png",
    "Coding problems",
    "Gay porn/Sine approximation",
    "Code/C,C++/Pointers",
    "Code/C,C++",
    "To-do notes",
    "Code",
    "Gay porn/Binary & Hex",
    "MCUs/STM32",
    "MCUs/Arduino",
    "MCUs"
  ]
}